mep/__init__.py
mep/callbacks.py
mep/models.py
mep/neb.py
mep/optimize.py
mep/path.py
mep/utils.py
mep-0.0.1.dist-info/LICENSE.md
mep-0.0.1.dist-info/METADATA
mep-0.0.1.dist-info/WHEEL
mep-0.0.1.dist-info/top_level.txt
mep-0.0.1.dist-info/RECORD
