Metadata-Version: 2.1
Name: mep
Version: 0.0.1
Summary: Minimal energy path tools for atomistic systems
Home-page: https://github.com/chc273/mep
Author: Chi Chen
Author-email: chc273@eng.ucsd.edu
License: BSD
Download-URL: https://github.com/chc273/mep
Keywords: materials,science,nudged elastic band
Platform: UNKNOWN
Classifier: Programming Language :: Python :: 3
Classifier: Programming Language :: Python :: 3.5
Classifier: Programming Language :: Python :: 3.6
Classifier: Programming Language :: Python :: 3.7
Classifier: Development Status :: 4 - Beta
Classifier: Intended Audience :: Science/Research
Classifier: License :: OSI Approved :: BSD License
Classifier: Operating System :: OS Independent
Classifier: Topic :: Scientific/Engineering :: Information Analysis
Classifier: Topic :: Scientific/Engineering :: Physics
Classifier: Topic :: Scientific/Engineering :: Chemistry
Classifier: Topic :: Software Development :: Libraries :: Python Modules
Requires-Dist: numpy
Requires-Dist: pymatgen
Requires-Dist: scipy
